apiframe_python/__init__.py
apiframe_python/main.py
apiframe-1.0.0.dist-info/METADATA
apiframe-1.0.0.dist-info/WHEEL
apiframe-1.0.0.dist-info/top_level.txt
apiframe-1.0.0.dist-info/RECORD
