Metadata-Version: 2.1
Name: apiframe
Version: 1.0.0
Summary: A Python client for the Apiframe API
Home-page: https://github.com/APIFRAME-PRO/apiframe-python
Author: APIFRAME.PRO
Author-email: hello@apiframe.pro
License: MIT
Keywords: apiframe,midjourney client,midjourney api,api midjourney,midjourney ai api,midjourney bot api,api midjourney api,api midjourney bot,midjourney api access
Requires-Dist: requests
